compressed_dictionary/__init__.py
compressed_dictionary/compressed_dictionary.py
compressed_dictionary/utils/__init__.py
compressed_dictionary/utils/merge.py
compressed_dictionary/utils/split.py
compressed_dictionary-1.2.1.dist-info/LICENSE
compressed_dictionary-1.2.1.dist-info/METADATA
compressed_dictionary-1.2.1.dist-info/WHEEL
compressed_dictionary-1.2.1.dist-info/top_level.txt
compressed_dictionary-1.2.1.dist-info/RECORD
