Metadata-Version: 2.1
Name: compressed-dictionary
Version: 1.2.1
Summary: A dictionary which values are automatically compressed to save memory.
Home-page: https://github.com/lucadiliello/compressed-dictionary.git
Author: Luca Di Liello
Author-email: luca.diliello@unitn.it
License: GNU v2
Platform: UNKNOWN
Classifier: Programming Language :: Python :: 3
Classifier: License :: OSI Approved :: GNU General Public License v2 (GPLv2)
Classifier: Operating System :: OS Independent
Classifier: Development Status :: 4 - Beta
Classifier: Natural Language :: English
Requires-Dist: tqdm
